py.typed
scnr2/__init__.py
scnr2/__init__.pyi
scnr2/py.typed
scnr2/scnr2.cpython-313-s390x-linux-gnu.so
scnr2-0.5.0.dist-info/METADATA
scnr2-0.5.0.dist-info/WHEEL
scnr2.pyi
scnr2-0.5.0.dist-info/RECORD
