Metadata-Version: 2.4
Name: scnr2
Version: 0.5.0
Classifier: Programming Language :: Rust
Classifier: Programming Language :: Python :: Implementation :: CPython
Classifier: License :: OSI Approved :: Apache Software License
Classifier: Operating System :: OS Independent
Classifier: Topic :: Software Development :: Compilers
Summary: Python bindings for scnr2
Author-email: Jörg Singer <singer.joerg@gmx.de>
Requires-Python: >=3.8
Project-URL: Bug Tracker, https://github.com/jsinger67/scnr2/issues
Project-URL: Homepage, https://github.com/jsinger67/scnr2
Project-URL: Repository, https://github.com/jsinger67/scnr2.git
